multiworld/__init__.py
multiworld/communicator.py
multiworld/init.txt
multiworld/manager.py
multiworld/post_setup.py
multiworld/threadsafe_async.py
multiworld/version.py
multiworld/watchdog.py
multiworld/patch/pytorch-v2.2.1-nccl.patch
multiworld/patch/pytorch-v2.2.1.patch
multiworld/patch/pytorch-v2.4.0.patch
multiworld-0.2.2.dist-info/licenses/LICENSE
multiworld-0.2.2.dist-info/METADATA
multiworld-0.2.2.dist-info/WHEEL
multiworld-0.2.2.dist-info/top_level.txt
multiworld-0.2.2.dist-info/RECORD
