Metadata-Version: 2.4
Name: multiworld
Version: 0.2.2
Summary: This package is a python library to support multiple communication groups for pytorch's distribted package
Author-email: Multiworld Maintainers <multiworld-maintainers@cisco.com>
Requires-Python: >=3.9
License-File: LICENSE
Requires-Dist: torch==2.4.0
Dynamic: license-file
